provworkflow/__init__.py
provworkflow/activity.py
provworkflow/agent.py
provworkflow/block.py
provworkflow/data_service.py
provworkflow/entity.py
provworkflow/error_entity.py
provworkflow/exceptions.py
provworkflow/git_utils.py
provworkflow/machine.py
provworkflow/namespace.py
provworkflow/person.py
provworkflow/prov_reporter.py
provworkflow/utils.py
provworkflow/workflow.py
provworkflow-0.3.0.dist-info/LICENSE
provworkflow-0.3.0.dist-info/METADATA
provworkflow-0.3.0.dist-info/WHEEL
provworkflow-0.3.0.dist-info/RECORD
